README.md
setup.py
alibabacloud_oss_sdk/__init__.py
alibabacloud_oss_sdk/client.py
alibabacloud_oss_sdk/models.py
alibabacloud_oss_sdk.egg-info/PKG-INFO
alibabacloud_oss_sdk.egg-info/SOURCES.txt
alibabacloud_oss_sdk.egg-info/dependency_links.txt
alibabacloud_oss_sdk.egg-info/requires.txt
alibabacloud_oss_sdk.egg-info/top_level.txt